EnMAP/6ABOS_EnMAP_AC_v1.2_Dic_2025.py
sixabos/__init__.py
sixabos/atmospheric.py
sixabos/config.py
sixabos/core.py
sixabos/main.py
sixabos/utils.py
sixabos-1.1.2.dist-info/licenses/LICENSE
sixabos-1.1.2.dist-info/METADATA
sixabos-1.1.2.dist-info/WHEEL
sixabos-1.1.2.dist-info/entry_points.txt
sixabos-1.1.2.dist-info/top_level.txt
sixabos-1.1.2.dist-info/RECORD
