Metadata-Version: 2.4
Name: sixabos
Version: 1.1.2
Summary: 6S-based Atmospheric Background Offset Subtraction for EnMAP Atmospheric Correction
Home-page: https://github.com/PhD-Gabriel-Caballero/6ABOS
Author: Gabriel Caballero
Author-email: Gabriel Caballero <gcaba@uv.es>
License: GPL-3.0-or-later
Project-URL: Homepage, https://github.com/PhD-Gabriel-Caballero/6ABOS
Project-URL: Bug Tracker, https://github.com/PhD-Gabriel-Caballero/6ABOS/issues
Project-URL: Documentation, https://github.com/PhD-Gabriel-Caballero/6ABOS/tree/main/docs
Project-URL: Change log, https://github.com/PhD-Gabriel-Caballero/6ABOS/blob/main/HISTORY.rst
Project-URL: Zenodo, https://zenodo.org/records/18232369
Classifier: Programming Language :: Python :: 3
Classifier: License :: OSI Approved :: GNU General Public License v3 (GPLv3)
Classifier: Operating System :: OS Independent
Classifier: Topic :: Scientific/Engineering :: GIS
Requires-Python: >=3.10
License-File: LICENSE
Requires-Dist: numpy
Requires-Dist: pandas
Requires-Dist: matplotlib
Requires-Dist: scipy
Requires-Dist: xmltodict
Requires-Dist: Py6S>=1.5.3
Requires-Dist: earthengine-api
Dynamic: author
Dynamic: home-page
Dynamic: license-file
Dynamic: requires-python
